COPYING
ChangeLog
DEPENDS
MANIFEST.in
README
TODO
announce.txt
logging.conf
setup.py
./__init__.py
./__pkginfo__.py
./commands.py
./main.py
./views.py
./checker/__init__.py
./checker/problem_checker.py
./lib/__init__.py
./lib/_exceptions.py
./lib/calendar.py
./lib/constants.py
./lib/project.py
./lib/resource.py
./lib/resource_role.py
./lib/task.py
./projmanedit/__init__.py
./projmanedit/main.py
./projmanedit/gui/__init__.py
./projmanedit/gui/taskedit.py
./readers/__init__.py
./readers/base_reader.py
./readers/projman_checkers.py
./readers/projman_reader.py
./renderers/__init__.py
./renderers/abstract.py
./renderers/colorutils.py
./renderers/gantt.py
./renderers/ganttresource.py
./renderers/html.py
./renderers/pil.py
./renderers/resource.py
./renderers/svg.py
./renderers/svg_cairo.py
./scheduling/__init__.py
./scheduling/basic.py
./scheduling/csp.py
./scheduling/dumb.py
./scheduling/noop.py
./scheduling/sample.py
./scheduling/simple.py
./test/__init__.py
./test/smoke_test.py
./test/unittest_commands.py
./test/unittest_lib_Calendar.py
./test/unittest_lib_Milestone.py
./test/unittest_lib_Project.py
./test/unittest_lib_Resource.py
./test/unittest_lib_ResourceSet.py
./test/unittest_lib_Task.py
./test/unittest_package.py
./test/unittest_reader_projman.py
./test/unittest_render.py
./test/unittest_scheduling.py
./writers/__init__.py
./writers/projman_writer.py
bin/projman
bin/projman.bat
data/projedit.glade
doc/INSTALL
doc/TODO
doc/format.txt
doc/makefile
doc/modele_argouml.zip
doc/spec.txt
doc/user_manual.xml
dtd/activities.dtd
dtd/catalog
dtd/project.dtd
dtd/projman.dtd
dtd/resources.dtd
dtd/schedule.dtd
examples/projman/full_activities.xml
examples/projman/full_projman.xml
examples/projman/full_resources.xml
examples/projman/full_schedule.xml
examples/projman/full_scheduled_projman.xml
examples/projman/full_tasks.xml
examples/projman/single_activity.xml
examples/projman/single_projman.xml
examples/projman/single_resource.xml
examples/projman/single_task.xml
projman.egg-info/PKG-INFO
projman.egg-info/SOURCES.txt
projman.egg-info/dependency_links.txt
projman.egg-info/top_level.txt
