Metadata-Version: 1.0
Name: projman
Version: 0.13.6
Summary: tool for project management
Home-page: http://www.logilab.org/projects/projman
Author: Logilab
Author-email: devel@logilab.fr
License: GPL
Platform: UNKNOWN
